slinkie.py
slinkie-1.1.0.dist-info/LICENSE
slinkie-1.1.0.dist-info/METADATA
slinkie-1.1.0.dist-info/WHEEL
slinkie-1.1.0.dist-info/top_level.txt
slinkie-1.1.0.dist-info/RECORD
