Metadata-Version: 2.1
Name: slinkie
Version: 1.1.0
Summary: Method chains for Python.
Home-page: http://segfaultsourcery.com/snippets/python/slinkie.html
Author: Kim Hermansson
Author-email: 
License: BSD
Keywords: productivity development method-chains functional linq kotlin
Platform: UNKNOWN
Classifier: Development Status :: 5 - Production/Stable
Classifier: Intended Audience :: Developers
Classifier: Topic :: Software Development :: Libraries
Classifier: License :: OSI Approved :: BSD License
Classifier: Programming Language :: Python :: 3.6
Classifier: Programming Language :: Python :: 3.7
Classifier: Programming Language :: Python :: 3.8
Requires-Python: ~=3.6
